nuuly_postgres_mcp_server/__init__.py
nuuly_postgres_mcp_server/__main__.py
nuuly_postgres_mcp_server/server.py
nuuly_postgres_mcp_server-1.0.1.dist-info/METADATA
nuuly_postgres_mcp_server-1.0.1.dist-info/WHEEL
nuuly_postgres_mcp_server-1.0.1.dist-info/entry_points.txt
nuuly_postgres_mcp_server-1.0.1.dist-info/top_level.txt
nuuly_postgres_mcp_server-1.0.1.dist-info/RECORD
