Metadata-Version: 2.4
Name: nuuly-postgres-mcp-server
Version: 1.0.1
Summary: MCP server for accessing Nuuly PostgreSQL database resources
Author-email: Nuuly Engineering <engineering@nuuly.com>
License: Proprietary
Project-URL: Homepage, https://github.com/urbn/r15-mcp
Project-URL: Repository, https://github.com/urbn/r15-mcp
Requires-Python: >=3.8
Requires-Dist: fastmcp>=2.2.1
Requires-Dist: httpx>=0.24.0
Requires-Dist: psycopg2-binary>=2.9.5
